miniflood/__init__.py
miniflood/flood.cp313-win_amd64.pyd
miniflood/version.py
miniflood/IO/__init__.py
miniflood/IO/version.py
miniflood/examples/case01/config.json
miniflood/examples/case01/dem.asc
miniflood-2.0.0.dist-info/METADATA
miniflood-2.0.0.dist-info/WHEEL
miniflood-2.0.0.dist-info/top_level.txt
miniflood-2.0.0.dist-info/RECORD
