Metadata-Version: 2.4
Name: miniflood
Version: 2.0.0
Summary: a demo 
Author: wang longyang
Author-email: 451215954@qq.com
License: GPLv3
Classifier: Development Status :: 3 - Alpha
Classifier: License :: OSI Approved :: GNU General Public License v3 or later (GPLv3+)
Classifier: Programming Language :: Python :: 3.13
Classifier: Programming Language :: C++
Classifier: Intended Audience :: Science/Research
Dynamic: author
Dynamic: author-email
Dynamic: classifier
Dynamic: description
Dynamic: description-content-type
Dynamic: license
Dynamic: summary
